prefect_earthdata/__init__.py
prefect_earthdata/_version.py
prefect_earthdata/credentials.py
prefect_earthdata/tasks.py
prefect_earthdata-0.1.3.dist-info/LICENSE
prefect_earthdata-0.1.3.dist-info/METADATA
prefect_earthdata-0.1.3.dist-info/WHEEL
prefect_earthdata-0.1.3.dist-info/entry_points.txt
prefect_earthdata-0.1.3.dist-info/top_level.txt
prefect_earthdata-0.1.3.dist-info/RECORD
